qpydoc/__init__.py
qpydoc/locales/en_US/LC_MESSAGES/messages.mo
qpydoc/locales/en_US/LC_MESSAGES/messages.po
qpydoc/locales/ko_KR/LC_MESSAGES/messages.mo
qpydoc/locales/ko_KR/LC_MESSAGES/messages.po
qpydoc-0.1.2.dist-info/METADATA
qpydoc-0.1.2.dist-info/WHEEL
qpydoc-0.1.2.dist-info/entry_points.txt
qpydoc-0.1.2.dist-info/top_level.txt
qpydoc-0.1.2.dist-info/RECORD
