Metadata-Version: 2.1
Name: qpydoc
Version: 0.1.2
Summary: Quarto-based Python API Documentation Tool
Author: KIM, Doh-Hyoung
Author-email: kim.dohhyoung@gmail.com
Keywords: quarto,api,documentation
Classifier: Development Status :: 4 - Beta
Classifier: Programming Language :: Python
Classifier: Programming Language :: Python :: 3.9
Classifier: Programming Language :: Python :: 3.10
Classifier: Programming Language :: Python :: 3.11
Requires-Python: >=3.9
Requires-Dist: regex
Requires-Dist: jupyter-cache
